init_mail/__init__.py
init_mail/__main__.py
init_mail/main.py
init_mail-0.1.8.dist-info/METADATA
init_mail-0.1.8.dist-info/WHEEL
init_mail-0.1.8.dist-info/entry_points.txt
init_mail-0.1.8.dist-info/RECORD
