Metadata-Version: 2.1
Name: init-mail
Version: 0.1.8
Summary: Added show_default=True for every options.
Home-page: https://github.com/vaibhavblayer/init-mail
Keywords: cli,email,gmail,mail
Author: vaibhavblayer
Author-email: vaibhavblayer@gmail.com
Requires-Python: >=3.11,<4.0
Classifier: Programming Language :: Python :: 3
Classifier: Programming Language :: Python :: 3.11
Project-URL: Repository, https://github.com/vaibhavblayer/init-mail
